MANIFEST.in
README.rst
setup.py
django_newsletter_form.egg-info/PKG-INFO
django_newsletter_form.egg-info/SOURCES.txt
django_newsletter_form.egg-info/SOURCES.txt.py
django_newsletter_form.egg-info/dependency_links.txt
django_newsletter_form.egg-info/dependency_links.txt.py
django_newsletter_form.egg-info/not-zip-safe
django_newsletter_form.egg-info/requires.txt
django_newsletter_form.egg-info/requires.txt.py
django_newsletter_form.egg-info/top_level.txt
django_newsletter_form.egg-info/top_level.txt.py
newsletter_form/__init__.py
newsletter_form/admin.py
newsletter_form/models.py
newsletter_form/settings.py
newsletter_form/urls.py
newsletter_form/views.py
newsletter_form/migrations/0001_initial.py
newsletter_form/migrations/0002_auto_20180329_1201.py
newsletter_form/migrations/__init__.py
newsletter_form/static/newsletter_form/css/newsletter_form.css
newsletter_form/static/newsletter_form/js/newsletter_form.js
newsletter_form/templates/newsletter_form/form_iscrizione_newsletter.html
newsletter_form/templates/newsletter_form/emails/base.html
newsletter_form/templates/newsletter_form/emails/iscrizione_confermata.html
newsletter_form/templatetags/__init__.py
newsletter_form/templatetags/newsletter_form_tags.py