Metadata-Version: 1.1
Name: django-newsletter-form
Version: 0.3.0
Summary: Simple Django newsletter form for Mailchimp
Home-page: http://github.com/b-dev/django-newsletter-form
Author: Marco Minutoli
Author-email: info@marcominutoli.it
License: MIT
Platform: UNKNOWN
Classifier: Environment :: Web Environment
Classifier: Framework :: Django
Classifier: Framework :: Django :: 1.11
Classifier: Intended Audience :: Developers
Classifier: License :: OSI Approved :: BSD License
Classifier: Operating System :: OS Independent
Classifier: Programming Language :: Python
Classifier: Programming Language :: Python :: 2
Classifier: Programming Language :: Python :: 2.7
Classifier: Topic :: Internet :: WWW/HTTP
Classifier: Topic :: Internet :: WWW/HTTP :: Dynamic Content
